promptimize/__init__.py
promptimize/cli.py
promptimize/crawler.py
promptimize/evals.py
promptimize/prompt_cases.py
promptimize/reports.py
promptimize/simple_jinja.py
promptimize/suite.py
promptimize/utils.py
promptimize-0.2.3.dist-info/LICENSE
promptimize-0.2.3.dist-info/METADATA
promptimize-0.2.3.dist-info/WHEEL
promptimize-0.2.3.dist-info/entry_points.txt
promptimize-0.2.3.dist-info/top_level.txt
promptimize-0.2.3.dist-info/RECORD
