Metadata-Version: 2.1
Name: promptimize
Version: 0.2.3
Summary: A python toolkit to generate and evaluate prompts for GPT at scale
Home-page: UNKNOWN
Author: Maxime Beauchemin
Author-email: maximebeauchemin@gmail.com
License: Apache License, Version 2.0
Platform: UNKNOWN
License-File: LICENSE
Requires-Dist: jinja2
Requires-Dist: python-box
Requires-Dist: black
Requires-Dist: click
Requires-Dist: pygments
Requires-Dist: pyyaml
Requires-Dist: langchain
Requires-Dist: tabulate
Requires-Dist: pandas
Requires-Dist: openai
